websnap-2.0.8.dist-info/METADATA
websnap-2.0.8.dist-info/WHEEL
websnap-2.0.8.dist-info/entry_points.txt
websnap-2.0.8.dist-info/licenses/LICENSE
websnap/__init__.py
websnap/config_templates/config_template.ini
websnap/config_templates/config_template.json
websnap/config_templates/s3_config_template.ini
websnap/config_templates/s3_config_template.json
websnap/constants.py
websnap/logger.py
websnap/logic.py
websnap/validators.py
websnap/websnap.py
websnap/websnap_cli.py
websnap-2.0.8.dist-info/RECORD
