Metadata-Version: 2.1
Name: websnap
Version: 2.0.8
Summary: Copies files retrieved from an API to an S3 bucket or a local machine.
Keywords: S3,Boto3,boto3,API,backup,AWS,AWS SDK,AWS SDK for Python
Author: Rebecca Buchholz
Maintainer-Email: EnviDat <envidat@wsl.ch>
License: MIT
Classifier: Programming Language :: Python :: 3
Classifier: Programming Language :: Python :: 3.11
Classifier: Programming Language :: Python :: 3.12
Classifier: Programming Language :: Python :: 3.13
Classifier: License :: OSI Approved :: MIT License
Classifier: Topic :: Internet
Classifier: Topic :: System
Classifier: Topic :: System :: Archiving
Classifier: Topic :: System :: Archiving :: Backup
Classifier: Topic :: System :: Archiving :: Mirroring
Classifier: Topic :: System :: Systems Administration
Classifier: Topic :: Utilities
Classifier: Intended Audience :: Developers
Classifier: Intended Audience :: System Administrators
Project-URL: documentation, https://github.com/EnviDat/websnap/blob/main/README.md
Project-URL: repository, https://github.com/EnviDat/websnap
Project-URL: changelog, https://github.com/EnviDat/websnap/blob/main/CHANGELOG.md
Requires-Python: >=3.11
Requires-Dist: pydantic>=2.7.4
Requires-Dist: boto3>=1.34.132
Requires-Dist: python-dotenv>=1.0.1
Requires-Dist: requests>=2.32.3
